{
  "sys": {
    "color": {
      "primary": {
        "default": {
          "value": "{ref.palette.primary.40}",
          "type": "color",
          "description": "primary"
        },
        "on-primary": {
          "value": "{ref.palette.primary.100}",
          "type": "color",
          "description": "on-primary"
        },
        "primary-container": {
          "value": "{ref.palette.primary.90}",
          "type": "color",
          "description": "primary-container"
        },
        "on-primary-container": {
          "value": "{ref.palette.primary.10}",
          "type": "color",
          "description": "on-primary-container"
        },
        "gradient": {
          "value": "linear-gradient(45deg, #ffffff 0%, #B9C4C7 50%, #000000 100%)",
          "type": "color",
          "description": "option for brand color gradient"
        }
      },
      "secondary": {
        "default": {
          "value": "{ref.palette.secondary.40}",
          "type": "color",
          "description": "secondary\n"
        },
        "on-secondary": {
          "value": "{ref.palette.secondary.100}",
          "type": "color",
          "description": "on-secondary\n"
        },
        "secondary-container": {
          "value": "{ref.palette.secondary.90}",
          "type": "color",
          "description": "secondary container"
        },
        "on-secondary-container": {
          "value": "{ref.palette.secondary.10}",
          "type": "color",
          "description": "on-secondary-container\n"
        },
        "gradient": {
          "value": "linear-gradient(45deg, #ffffff 0%, #939094 50%, #1F1B1B 100%)",
          "type": "color",
          "description": "option if brand has secondary gradient"
        }
      },
      "error": {
        "default": {
          "value": "{ref.palette.red.40}",
          "type": "color"
        },
        "on-error": {
          "value": "{ref.palette.red.100}",
          "type": "color"
        },
        "error-container": {
          "value": "{ref.palette.red.80}",
          "type": "color"
        },
        "on-error-container": {
          "value": "{ref.palette.red.10}",
          "type": "color"
        }
      },
      "success": {
        "default": {
          "value": "{ref.palette.green.40}",
          "type": "color",
          "description": "Success icons, outlines, highlights, etc"
        },
        "on-success": {
          "value": "{ref.palette.green.100}",
          "type": "color"
        },
        "success-container": {
          "value": "{ref.palette.green.90}",
          "type": "color"
        },
        "on-success-container": {
          "value": "{ref.palette.green.10}",
          "type": "color"
        }
      },
      "caution": {
        "default": {
          "value": "{ref.palette.yellow.40}",
          "type": "color",
          "description": "Caution icons, outlines, highlights, etc"
        },
        "on-caution": {
          "value": "{ref.palette.yellow.100}",
          "type": "color"
        },
        "caution-container": {
          "value": "{ref.palette.yellow.90}",
          "type": "color"
        },
        "on-caution-container": {
          "value": "{ref.palette.yellow.10}",
          "type": "color"
        }
      },
      "warning": {
        "default": {
          "value": "{ref.palette.orange.40}",
          "type": "color",
          "description": "Warning icons, outlines, highlights, etc"
        },
        "on-warning": {
          "value": "{ref.palette.orange.100}",
          "type": "color"
        },
        "warning-container": {
          "value": "{ref.palette.orange.90}",
          "type": "color"
        },
        "on-warning-container": {
          "value": "{ref.palette.orange.10}",
          "type": "color"
        }
      },
      "surface": {
        "0": {
          "value": "{ref.palette.primary.100}",
          "type": "color",
          "description": "Base"
        },
        "1": {
          "value": "{ref.palette.primary.99}",
          "type": "color",
          "description": "base color"
        },
        "2": {
          "value": "{ref.palette.neutral.90}",
          "type": "color",
          "description": "surface2",
          "$extensions": {
            "studio.tokens": {
              "modify": {
                "type": "mix",
                "value": "0.35",
                "space": "lch",
                "color": "{ref.palette.neutral.100}"
              }
            }
          }
        },
        "3": {
          "value": "{ref.palette.neutral.90}",
          "type": "color",
          "description": "surface3",
          "$extensions": {
            "studio.tokens": {
              "modify": {
                "type": "mix",
                "value": "0.1",
                "space": "lch",
                "color": "{ref.palette.neutral.100}"
              }
            }
          }
        },
        "on-base": {
          "value": "{ref.palette.primary.10}",
          "type": "color",
          "description": "content on top of base"
        },
        "on-surface-variant": {
          "value": "{ref.palette.neutral-variant.30}",
          "type": "color",
          "description": "on surface variant"
        },
        "inverse": {
          "value": "{ref.palette.neutral.20}",
          "type": "color",
          "description": "inverse surface"
        },
        "on-surface": {
          "value": "{ref.palette.neutral-variant.10}",
          "type": "color",
          "description": "typography and high emphasis elements on surfaces"
        },
        "disabled": {
          "value": "#949290",
          "type": "color",
          "description": "disabled containers/icons\nNV10@46% converted to hex"
        },
        "disabled-container": {
          "value": "{ref.palette.neutral-variant.10}",
          "type": "color",
          "description": "disabled container",
          "$extensions": {
            "studio.tokens": {
              "modify": {
                "type": "mix",
                "value": "0.82",
                "space": "lch",
                "color": "{ref.palette.neutral-variant.100}"
              }
            }
          }
        },
        "surface-variant": {
          "value": "{ref.palette.neutral-variant.90}",
          "type": "color",
          "description": "alternate surface color"
        }
      }
    },
    "type": {
      "h1": {
        "value": {
          "fontFamily": "{ref.font-family.heading}",
          "fontWeight": "{ref.typeface.weight-bold}",
          "lineHeight": "{ref.line-height.heading}",
          "fontSize": "{ref.typescale.heading.h1}",
          "letterSpacing": "{ref.letter-spacing.default}",
          "paragraphSpacing": "{ref.paragraph-spacing.h1}"
        },
        "type": "typography",
        "description": "h1"
      }
    }
  }
}